{
  "tec_type": "STOR",
  "size_min": 0,
  "size_max": 28000,
  "size_is_int": 0,
  "decommission": 0,
  "decommission_full": 0,
  "Economics": {
    "comment": "CAPEX in EUR/MWh or as a piecewise function, OPEX_variable in EUR/MWh total output, OPEX_fixed in % of CAPEX_annual",
    "CAPEX_model": 1,
    "unit_CAPEX": 10000,
    "fix_CAPEX": 0,
    "piecewise_CAPEX": {
      "bp_x": [
        0,
        28,
        114,
        28000
      ],
      "bp_y": [
        0,
        294649,
        941687,
        1.75229187E+8
      ]
    },
    "OPEX_variable": 0,
    "OPEX_fixed": 0.02,
    "discount_rate": 0.1,
    "lifetime": 20,
    "decommission_cost": 0
  },
  "Performance": {
    "comment": "contains fitting data on unit of input, technology types and input/output carriers",
    "input_carrier": [
      "heat"
    ],
    "main_input_carrier": "heat",
    "output_carrier": [
      "heat"
    ],
    "emission_factor": 0,
    "allow_only_one_direction": 1,
    "performance": {
      "eta_in": 0.95,
      "eta_out": 0.95,
      "lambda": 0.005,
      "theta": 0.0005
    }
  },
  "Flexibility": {
    "comment": "determines the flexibility of the power capacity compared to the energy capacity",
    "power_energy_ratio": "fixedratio",
    "charge_rate": 0.33333333333333331,
    "discharge_rate": 0.33333333333333331,
    "capex_charging_power": 0,
    "capex_discharging_power": 0
  },
  "Units": {
    "size": "MWh",
    "input_carrier": {
      "heat": "MW"
    },
    "output_carrier": {
      "heat": "MW"
    }
  }
}